MANIFEST.in
README.rst
setup.py
Watson_CT.egg-info/PKG-INFO
Watson_CT.egg-info/SOURCES.txt
Watson_CT.egg-info/dependency_links.txt
Watson_CT.egg-info/requires.txt
Watson_CT.egg-info/top_level.txt
watson/__init__.py
watson/core.py
watson/discover.py
watson/models.py
watson/runner.py
watson/management/__init__.py
watson/management/commands/__init__.py
watson/management/commands/drwatson.py
watson/ui/__init__.py
watson/ui/base.py
watson/ui/growl2.py
watson/ui/terminal_notifier.py
watson/ui/img/green.png
watson/ui/img/red.png