Metadata-Version: 1.0
Name: Watson-CT
Version: 0.2.0
Summary: Continuous unit test runner for django
Home-page: http://github.com/puffin/watson
Author: David Michon
Author-email: david.michon@gmail.com
License: BSD
Platform: UNKNOWN
